setup.py
mle_udacity_dist_test/Binomialdistribution.py
mle_udacity_dist_test/Gaussiandistribution.py
mle_udacity_dist_test/Generaldistribution.py
mle_udacity_dist_test/__init__.py
mle_udacity_dist_test.egg-info/PKG-INFO
mle_udacity_dist_test.egg-info/SOURCES.txt
mle_udacity_dist_test.egg-info/dependency_links.txt
mle_udacity_dist_test.egg-info/not-zip-safe
mle_udacity_dist_test.egg-info/top_level.txt