Metadata-Version: 1.0
Name: mle-udacity-dist-test
Version: 0.1
Summary: Gaussian distributions
Home-page: UNKNOWN
Author: coding maggie
Author-email: UNKNOWN
License: UNKNOWN
Platform: UNKNOWN
